{
  "schemaVersion": "pccx.lab.mcp-read-only-report-contract.v0",
  "tool": "pccx-lab",
  "contractId": "mcp-read-only-report-cli-core-contract",
  "contractState": "descriptor_only",
  "adapterState": "not_implemented",
  "defaultMode": "read_only",
  "automationPath": "cli-core-first-gui-independent",
  "entryBoundaryRefs": [
    {
      "refId": "analysis_flow",
      "schemaVersion": "pccx.lab.mcp-read-only-analysis-flow.v0",
      "examplePath": "docs/examples/mcp-read-only-analysis-flow.example.json",
      "state": "available_as_data"
    },
    {
      "refId": "tool_plan",
      "schemaVersion": "pccx.lab.mcp-read-only-tool-plan.v0",
      "examplePath": "docs/examples/mcp-read-only-tool-plan.example.json",
      "state": "available_as_data"
    },
    {
      "refId": "permission_model",
      "schemaVersion": "pccx.lab.mcp-permission-model.v0",
      "examplePath": "docs/examples/mcp-permission-model.example.json",
      "state": "available_as_data"
    },
    {
      "refId": "audit_event_shape",
      "schemaVersion": "pccx.lab.mcp-audit-event.v0",
      "examplePath": "docs/examples/mcp-audit-event.example.json",
      "state": "available_as_data"
    }
  ],
  "reportSections": [
    {
      "sectionId": "lab_status_summary",
      "sourceBoundary": "pccx.lab.status.v0",
      "outputKind": "status_summary_section",
      "sectionState": "example_only",
      "summary": "Conservative lab status and evidence markers.",
      "summaryOnly": true,
      "itemLimit": 4,
      "artifactWrite": false,
      "repositoryMutation": false,
      "privatePathEchoAllowed": false,
      "stdoutIncluded": false,
      "stderrIncluded": false,
      "rawLogIncluded": false,
      "fieldDescriptors": [
        {
          "fieldName": "labMode",
          "valueKind": "bounded-string",
          "policy": "copied from status JSON only"
        },
        {
          "fieldName": "evidenceState",
          "valueKind": "metadata-object",
          "policy": "conservative marker values only; no hardware proof is implied"
        }
      ]
    },
    {
      "sectionId": "workflow_descriptor_summary",
      "sourceBoundary": "pccx.lab.workflow-descriptors.v0",
      "outputKind": "descriptor_catalog_section",
      "sectionState": "example_only",
      "summary": "Descriptor-only workflow catalog summary.",
      "summaryOnly": true,
      "itemLimit": 8,
      "artifactWrite": false,
      "repositoryMutation": false,
      "privatePathEchoAllowed": false,
      "stdoutIncluded": false,
      "stderrIncluded": false,
      "rawLogIncluded": false,
      "fieldDescriptors": [
        {
          "fieldName": "workflowId",
          "valueKind": "bounded-string",
          "policy": "descriptor identifier only"
        },
        {
          "fieldName": "executionState",
          "valueKind": "enum",
          "policy": "must remain descriptor-only in this fixture"
        }
      ]
    },
    {
      "sectionId": "workflow_proposal_preview",
      "sourceBoundary": "pccx.lab.workflow-proposals.v0",
      "outputKind": "proposal_preview_section",
      "sectionState": "example_only",
      "summary": "Proposal-only command previews without execution.",
      "summaryOnly": true,
      "itemLimit": 8,
      "artifactWrite": false,
      "repositoryMutation": false,
      "privatePathEchoAllowed": false,
      "stdoutIncluded": false,
      "stderrIncluded": false,
      "rawLogIncluded": false,
      "fieldDescriptors": [
        {
          "fieldName": "proposalId",
          "valueKind": "bounded-string",
          "policy": "proposal identifier only"
        },
        {
          "fieldName": "fixedArgsPreview",
          "valueKind": "bounded-string-array",
          "policy": "structured argument preview; not a shell command string"
        }
      ]
    },
    {
      "sectionId": "workflow_result_summary",
      "sourceBoundary": "pccx.lab.workflow-results.v0",
      "outputKind": "result_summary_section",
      "sectionState": "example_only",
      "summary": "Summary-only workflow result metadata without full logs.",
      "summaryOnly": true,
      "itemLimit": 8,
      "artifactWrite": false,
      "repositoryMutation": false,
      "privatePathEchoAllowed": false,
      "stdoutIncluded": false,
      "stderrIncluded": false,
      "rawLogIncluded": false,
      "fieldDescriptors": [
        {
          "fieldName": "status",
          "valueKind": "enum",
          "policy": "copied from workflow result summary status"
        },
        {
          "fieldName": "summary",
          "valueKind": "bounded-string",
          "policy": "summary-only; no stdout, stderr, or raw logs"
        }
      ]
    }
  ],
  "sampleReport": {
    "reportId": "mcp-read-only-report-example",
    "reportState": "summary_only_fixture",
    "reportFormat": "bounded_json_summary",
    "overallStatus": "not_executed",
    "createdAt": "not-recorded",
    "sections": [
      {
        "sectionId": "lab_status_summary",
        "title": "Lab status",
        "summary": "Host status is available as deterministic metadata; hardware, timing, inference, and throughput remain unclaimed.",
        "sourceRef": "run-status.example.json",
        "evidenceState": "metadata-only",
        "itemCount": 1,
        "pathIncluded": false,
        "artifactWrite": false
      },
      {
        "sectionId": "workflow_descriptor_summary",
        "title": "Workflow descriptors",
        "summary": "Workflow descriptors are available as descriptor-only metadata.",
        "sourceRef": "workflow-descriptors.example.json",
        "evidenceState": "metadata-only",
        "itemCount": 4,
        "pathIncluded": false,
        "artifactWrite": false
      },
      {
        "sectionId": "workflow_proposal_preview",
        "title": "Workflow proposals",
        "summary": "Workflow proposals are previews only and do not execute commands.",
        "sourceRef": "workflow-proposals.example.json",
        "evidenceState": "metadata-only",
        "itemCount": 4,
        "pathIncluded": false,
        "artifactWrite": false
      },
      {
        "sectionId": "workflow_result_summary",
        "title": "Workflow results",
        "summary": "Workflow result summaries omit stdout, stderr, raw logs, generated artifacts, hardware logs, and provider logs.",
        "sourceRef": "workflow-results.example.json",
        "evidenceState": "summary-only",
        "itemCount": 1,
        "pathIncluded": false,
        "artifactWrite": false
      }
    ],
    "trackedFileMutation": false,
    "artifactWrite": false,
    "pathEchoAllowed": false,
    "stdoutIncluded": false,
    "stderrIncluded": false,
    "rawLogIncluded": false,
    "privatePathsIncluded": false,
    "generatedArtifactsIncluded": false
  },
  "outputPolicy": {
    "state": "planned",
    "summaryOnly": true,
    "approvalRequiredForPathInputs": true,
    "auditRequired": true,
    "commandExecutionByFixture": false,
    "trackedFileMutationAllowed": false,
    "artifactWriteAllowed": false,
    "pathEchoAllowed": false,
    "stdoutAllowed": false,
    "stderrAllowed": false,
    "rawLogAllowed": false,
    "privatePathsAllowed": false,
    "generatedArtifactsAllowed": false,
    "noMutationRule": "Future validation must prove tracked files are unchanged before and after producing a read-only analysis report.",
    "redactionRule": "Report output must omit private paths, secrets, tokens, model paths, stdout, stderr, raw logs, and generated artifact paths."
  },
  "blockedActions": [
    "mcp-server-start",
    "mcp-client-session",
    "arbitrary-shell-command",
    "approved-workflow-run",
    "artifact-write",
    "repository-write-back",
    "public-push",
    "release-or-tag",
    "provider-call",
    "network-call",
    "hardware-probe",
    "kv260-access",
    "fpga-repo-access",
    "runtime-launch",
    "model-load",
    "telemetry-upload"
  ],
  "safetyFlags": {
    "dataOnly": true,
    "descriptorOnly": true,
    "readOnly": true,
    "reportFixtureOnly": true,
    "mcpRuntimeImplemented": false,
    "mcpServerImplemented": false,
    "mcpClientImplemented": false,
    "commandExecution": false,
    "shellExecution": false,
    "runtimeExecution": false,
    "networkCalls": false,
    "providerCalls": false,
    "launcherExecution": false,
    "editorExecution": false,
    "hardwareAccess": false,
    "kv260Access": false,
    "fpgaRepoAccess": false,
    "modelExecution": false,
    "modelWeightsIncluded": false,
    "privatePathsIncluded": false,
    "secretsIncluded": false,
    "tokensIncluded": false,
    "stdoutIncluded": false,
    "stderrIncluded": false,
    "rawLogsIncluded": false,
    "telemetry": false,
    "writeBack": false,
    "writesArtifacts": false,
    "publicPush": false,
    "releaseOrTag": false,
    "stableApiAbiClaim": false
  },
  "limitations": [
    "This is a checked read-only report contract fixture, not an MCP server, client, runtime, command executor, or report writer.",
    "The sample report is descriptor-only metadata assembled from bounded CLI/core summaries; it does not execute commands or write reports.",
    "No private paths, full logs, generated artifacts, secrets, tokens, provider configuration, model paths, hardware access, or repository mutation are included.",
    "No release, tag, compatibility, hardware, inference, throughput, or timing-closure claim is made."
  ],
  "issueRefs": [
    "pccxai/pccx-lab#22"
  ]
}
